scraper_engine_v2/__init__.py
scraper_engine_v2/wrapper.py
scraper_engine_v2-0.1.0.dist-info/LICENSE
scraper_engine_v2-0.1.0.dist-info/METADATA
scraper_engine_v2-0.1.0.dist-info/WHEEL
scraper_engine_v2-0.1.0.dist-info/top_level.txt
scraper_engine_v2-0.1.0.dist-info/RECORD
