Metadata-Version: 2.1
Name: scraper_engine_v2
Version: 0.1.0
Summary: Ultimate scraping engine powered by Chromium
Home-page: https://github.com/Wimtop/scraper_engine_v2
Author: Wimtop
License: GNU GENERAL PUBLIC LICENSE
Classifier: Programming Language :: Python :: 3
Classifier: Operating System :: OS Independent
License-File: LICENSE
Requires-Dist: requests
Requires-Dist: requests-toolbelt
